pynotes/__init__.py
pynotes/__main__.py
pynotes/add_link/__init__.py
pynotes/add_link/append_md_link.py
pynotes/add_link/format_link.py
pynotes/add_tag/__init__.py
pynotes/add_tag/append_md_tag.py
pynotes/add_tag/format_tag.py
pynotes/add_tag/get_all_lines.py
pynotes/add_tag/get_tag_line.py
pynotes/add_tag/update_tag_line.py
pynotes/helpers/__init__.py
pynotes/helpers/file_exist.py
pynotes/links/__init__.py
pynotes/links/get_links.py
pynotes/new_note/__init__.py
pynotes/new_note/write_md_file.py
pynotes/read/__init__.py
pynotes/tags/__init__.py
pynotes/tags/get_tags.py
pynotes-0.1.2.dist-info/METADATA
pynotes-0.1.2.dist-info/RECORD
pynotes-0.1.2.dist-info/WHEEL
pynotes-0.1.2.dist-info/entry_points.txt
pynotes-0.1.2.dist-info/top_level.txt
