Metadata-Version: 2.1
Name: pynotes
Version: 0.1.2
Summary: Create daily notes/log with markdown.
Home-page: http://github.com/afonsopacifer/pynotes
Author: Afonso Pacifer
Author-email: afonsopacifer@live.com
License: MIT
Platform: UNKNOWN
